speedyfit/__init__.py
speedyfit/calibration.py
speedyfit/default_setup.py
speedyfit/fileio.py
speedyfit/filters.py
speedyfit/integrate_grid.py
speedyfit/interpol.py
speedyfit/main.py
speedyfit/mcmc.py
speedyfit/model.py
speedyfit/photometry_query.py
speedyfit/plotting.py
speedyfit/reddening.py
speedyfit/speedyfit_batch.py
speedyfit/statfunc.py
speedyfit/tap_cats_phot.cfg
speedyfit/utils.py
speedyfit/vizier_cats_phot.cfg
speedyfit/zeropoints.dat
speedyfit/redlaws/Chiar2006.red
speedyfit/redlaws/Fitzpatrick1999_Rv_2_1.red
speedyfit/redlaws/Fitzpatrick1999_Rv_3_1.red
speedyfit/redlaws/Fitzpatrick1999_Rv_5_0.red
speedyfit/redlaws/Fitzpatrick2004_Rv_2.1.red
speedyfit/redlaws/Fitzpatrick2004_Rv_2.2.red
speedyfit/redlaws/Fitzpatrick2004_Rv_2.3.red
speedyfit/redlaws/Fitzpatrick2004_Rv_2.4.red
speedyfit/redlaws/Fitzpatrick2004_Rv_2.5.red
speedyfit/redlaws/Fitzpatrick2004_Rv_2.6.red
speedyfit/redlaws/Fitzpatrick2004_Rv_2.7.red
speedyfit/redlaws/Fitzpatrick2004_Rv_2.8.red
speedyfit/redlaws/Fitzpatrick2004_Rv_2.9.red
speedyfit/redlaws/Fitzpatrick2004_Rv_3.0.red
speedyfit/redlaws/Fitzpatrick2004_Rv_3.1.red
speedyfit/redlaws/Fitzpatrick2004_Rv_3.2.red
speedyfit/redlaws/Fitzpatrick2004_Rv_3.3.red
speedyfit/redlaws/Fitzpatrick2004_Rv_3.4.red
speedyfit/redlaws/Fitzpatrick2004_Rv_3.5.red
speedyfit/redlaws/Fitzpatrick2004_Rv_3.6.red
speedyfit/redlaws/Fitzpatrick2004_Rv_3.7.red
speedyfit/redlaws/Fitzpatrick2004_Rv_3.8.red
speedyfit/redlaws/Fitzpatrick2004_Rv_3.9.red
speedyfit/redlaws/Fitzpatrick2004_Rv_4.0.red
speedyfit/redlaws/Fitzpatrick2004_Rv_4.1.red
speedyfit/redlaws/Fitzpatrick2004_Rv_4.2.red
speedyfit/redlaws/Fitzpatrick2004_Rv_4.3.red
speedyfit/redlaws/Fitzpatrick2004_Rv_4.4.red
speedyfit/redlaws/Fitzpatrick2004_Rv_4.5.red
speedyfit/redlaws/Fitzpatrick2004_Rv_4.6.red
speedyfit/redlaws/Fitzpatrick2004_Rv_4.7.red
speedyfit/redlaws/Fitzpatrick2004_Rv_4.8.red
speedyfit/redlaws/Fitzpatrick2004_Rv_4.9.red
speedyfit/redlaws/Fitzpatrick2004_Rv_5.0.red
speedyfit-0.2.5.dist-info/LICENSE
speedyfit-0.2.5.dist-info/METADATA
speedyfit-0.2.5.dist-info/WHEEL
speedyfit-0.2.5.dist-info/entry_points.txt
speedyfit-0.2.5.dist-info/top_level.txt
speedyfit-0.2.5.dist-info/RECORD
