Metadata-Version: 2.1
Name: speedyfit
Version: 0.2.5
Summary: MC approach to fit photometric SEDs
Home-page: https://github.com/vosjo/speedyfit
Author: Joris Vos
Author-email: joris.vos@uv.cl
Classifier: Development Status :: 5 - Production/Stable
Classifier: Environment :: Console
Classifier: Programming Language :: Python :: 3
Classifier: License :: OSI Approved :: GNU General Public License v3 (GPLv3)
Classifier: Operating System :: OS Independent
Classifier: Topic :: Scientific/Engineering :: Astronomy
Requires-Python: >=3.9
License-File: LICENSE
Requires-Dist: numpy
Requires-Dist: emcee
Requires-Dist: astropy>=5.1
Requires-Dist: astroquery>=0.4.10
Requires-Dist: pyvo>=1.4
Requires-Dist: matplotlib
Requires-Dist: pyaml
Requires-Dist: corner
Requires-Dist: tqdm
Requires-Dist: scipy
Requires-Dist: h5py
Requires-Dist: pandas
Requires-Dist: gaiadr3-zeropoint
Requires-Dist: pytz
